COPYING.txt
MANIFEST.in
README.rst
setup.cfg
setup.py
dtcwt/__init__.py
dtcwt/_version.py
dtcwt/coeffs.py
dtcwt/compat.py
dtcwt/defaults.py
dtcwt/keypoint.py
dtcwt/plotting.py
dtcwt/registration.py
dtcwt/sampling.py
dtcwt/utils.py
dtcwt.egg-info/PKG-INFO
dtcwt.egg-info/SOURCES.txt
dtcwt.egg-info/dependency_links.txt
dtcwt.egg-info/requires.txt
dtcwt.egg-info/top_level.txt
dtcwt/data/antonini.npz
dtcwt/data/legall.npz
dtcwt/data/near_sym_a.npz
dtcwt/data/near_sym_b.npz
dtcwt/data/near_sym_b_bp.npz
dtcwt/data/qshift_06.npz
dtcwt/data/qshift_32.npz
dtcwt/data/qshift_a.npz
dtcwt/data/qshift_b.npz
dtcwt/data/qshift_b_bp.npz
dtcwt/data/qshift_c.npz
dtcwt/data/qshift_d.npz
dtcwt/numpy/__init__.py
dtcwt/numpy/common.py
dtcwt/numpy/lowlevel.py
dtcwt/numpy/transform1d.py
dtcwt/numpy/transform2d.py
dtcwt/numpy/transform3d.py
dtcwt/opencl/__init__.py
dtcwt/opencl/lowlevel.py
dtcwt/opencl/transform2d.py
dtcwt/opencl/transform3d.py
dtcwt/tf/__init__.py
dtcwt/tf/common.py
dtcwt/tf/lowlevel.py
dtcwt/tf/transform1d.py
dtcwt/tf/transform2d.py
tests/test_againstmatlab.py
tests/test_coeffs.py
tests/test_coldfilt.py
tests/test_colfilter.py
tests/test_colifilt.py
tests/test_ifm1.py
tests/test_ifm2.py
tests/test_import.py
tests/test_openclcoldfilt.py
tests/test_openclcolfilter.py
tests/test_openclcolifilt.py
tests/test_openclxfm2.py
tests/test_reflect.py
tests/test_registration.py
tests/test_sampling.py
tests/test_switchbackends.py
tests/test_tfTransform1d.py
tests/test_tfTransform2d.py
tests/test_tfcoldfilt.py
tests/test_tfcolfilter.py
tests/test_tfcolifilt.py
tests/test_tfinputshapes.py
tests/test_tfrowdfilt.py
tests/test_tfrowfilter.py
tests/test_utils.py
tests/test_xfm1.py
tests/test_xfm2.py
tests/test_xfm3.py