Metadata-Version: 2.1
Name: dtcwt
Version: 0.13.0
Summary: A port of the Dual-Tree Complex Wavelet Transform MATLAB toolbox.
Home-page: https://github.com/rjw57/dtcwt
Author: Rich Wareham
Author-email: rich.dtcwt@richwareham.com
License: Free To Use But Restricted
Keywords: numpy,wavelet,complex wavelet,DT-CWT
Classifier: Development Status :: 3 - Alpha
Classifier: License :: Free To Use But Restricted
Classifier: Programming Language :: Python :: 2
Classifier: Programming Language :: Python :: 3
License-File: COPYING.txt
Requires-Dist: numpy
Requires-Dist: six
Provides-Extra: docs
Requires-Dist: sphinx; extra == "docs"
Requires-Dist: docutils; extra == "docs"
Requires-Dist: matplotlib; extra == "docs"
Requires-Dist: ipython; extra == "docs"
Provides-Extra: opencl
Requires-Dist: pyopencl; extra == "opencl"
